[
    {
        "category": "",

        "questions": [
            {
                "points": 400,
                "fontColor": "#f5de50",
                "question": "",
                "answer": "",
                "isDailyDouble": false
            },
            {
                "points": 800,
                "fontColor": "#f5de50",
                "question": "",
                "answer": "",
                "isDailyDouble": false
            },
            {
                "points": 1200,
                "fontColor": "#f5de50",
                "question": "",
                "answer": "",
                "isDailyDouble": false
            },
            {
                "points": 1600,
                "fontColor": "#f5de50",
                "question": "",
                "answer": "",
                "isDailyDouble": false
            },
            {
                "points": 2000,
                "fontColor": "#f5de50",
                "question": "",
                "answer": "",
                "isDailyDouble": false
            }
        ]
    }
]